sxclient-0.19.0.dist-info/top_level.txt
sxclient-0.19.0.dist-info/RECORD
sxclient-0.19.0.dist-info/METADATA
sxclient-0.19.0.dist-info/DESCRIPTION.rst
sxclient-0.19.0.dist-info/WHEEL
sxclient-0.19.0.dist-info/metadata.json
sxclient/exceptions.py
sxclient/cache.py
sxclient/defaults.py
sxclient/__init__.py
sxclient/controller.py
sxclient/query/utils.py
sxclient/query/auth.py
sxclient/query/__init__.py
sxclient/query/hostname_adapter.py
sxclient/query/cluster_session.py
sxclient/query/query_handler.py
sxclient/models/user_data.py
sxclient/models/__init__.py
sxclient/models/cluster.py
sxclient/models/query_parameters.py
sxclient/tools/blocks_generator.py
sxclient/tools/filters.py
sxclient/tools/__init__.py
sxclient/tools/file_downloader.py
sxclient/tools/address_helpers.py
sxclient/tools/string_helpers.py
sxclient/tools/file_cat.py
sxclient/tools/file_uploader.py
sxclient/tools/thread_pool.py
sxclient/operations/user.py
sxclient/operations/base.py
sxclient/operations/__init__.py
sxclient/operations/cluster.py
sxclient/operations/volume.py
sxclient/operations/multiple_files.py
sxclient/operations/blocks.py
sxclient/operations/volume_acl.py
sxclient/operations/single_file.py
sxclient/operations/node.py
