Metadata-Version: 2.0
Name: sxclient
Version: 0.19.0
Summary: Python SX client-side library
Home-page: http://www.skylable.com/docs/client-libraries/python-sxclient
Author: Skylable Ltd.
Author-email: sx-users@lists.skylable.com
License: Apache 2.0
Platform: UNKNOWN
Classifier: Development Status :: 4 - Beta
Classifier: Intended Audience :: Developers
Classifier: Natural Language :: English
Classifier: License :: OSI Approved :: Apache Software License
Classifier: Programming Language :: Python
Classifier: Programming Language :: Python :: 2.7
Requires-Dist: requests (==2.9.1)
Requires-Dist: py-bcrypt (==0.4)
Requires-Dist: dogpile.cache (==0.5.7)
Requires-Dist: six (>=1.10.0)
Requires-Dist: typing (>=3.5.2.2)
